setup.cfg
setup.py
simdb/__init__.py
simdb/db.py
simdb/run.py
simdb.egg-info/PKG-INFO
simdb.egg-info/SOURCES.txt
simdb.egg-info/dependency_links.txt
simdb.egg-info/requires.txt
simdb.egg-info/top_level.txt