Metadata-Version: 1.1
Name: simdb
Version: 0.3.0
Summary: A simple Python package for management of simulation datasets
Home-page: https://github.com/sdrave/simdb
Author: Stephan Rave
Author-email: mail@stephanrave.de
License: BSD License
Keywords: simulation data numerics reproducibility
Platform: UNKNOWN
Classifier: Development Status :: 3 - Alpha
Classifier: Intended Audience :: Developers
Classifier: Intended Audience :: Science/Research
Classifier: Topic :: Scientific/Engineering
Classifier: Topic :: Software Development :: Libraries
Classifier: Topic :: Database
Classifier: License :: OSI Approved :: BSD License
Classifier: Programming Language :: Python :: 2
Classifier: Programming Language :: Python :: 2.7
